[
  {
    "hot_word": "你好李焕英票房破10亿",
    "hot_word_num": "367584"
  },
  {
    "hot_word": "研究称美国去年7月已出现变异新冠病毒",
    "hot_word_num": "276615"
  },
  {
    "hot_word": "范迪塞尔的新年装备",
    "hot_word_num": "273478"
  },
  {
    "hot_word": "张大大 原来让人讨厌这么难",
    "hot_word_num": "266158"
  },
  {
    "hot_word": "宋轶好美",
    "hot_word_num": "246155"
  },
  {
    "hot_word": "邓超送给孙俪自己种的花",
    "hot_word_num": "165521"
  },
  {
    "hot_word": "赘婿",
    "hot_word_num": "157848"
  },
  {
    "hot_word": "沈腾直男式示爱",
    "hot_word_num": "113984"
  },
  {
    "hot_word": "几内亚出现5年来首批埃博拉死亡病例",
    "hot_word_num": "113881"
  },
  {
    "hot_word": "郭麒麟演技",
    "hot_word_num": "113803"
  },
  {
    "hot_word": "被文咏珊惊艳到",
    "hot_word_num": "97661"
  },
  {
    "hot_word": "吐槽大会",
    "hot_word_num": "97580"
  },
  {
    "hot_word": "苏檀儿主动吻宁毅",
    "hot_word_num": "97128"
  },
  {
    "hot_word": "牛年只有23个节气",
    "hot_word_num": "96463"
  },
  {
    "hot_word": "蒙淇淇凡尔赛式吐槽",
    "hot_word_num": "96053"
  },
  {
    "hot_word": "翁丁大火",
    "hot_word_num": "96018"
  },
  {
    "hot_word": "Angelababy还好我是南方人",
    "hot_word_num": "95259"
  },
  {
    "hot_word": "上海就地过年带动酒店业",
    "hot_word_num": "95186"
  },
  {
    "hot_word": "俄批准与中国合建月球科研站计划",
    "hot_word_num": "94748"
  },
  {
    "hot_word": "唐探3票房",
    "hot_word_num": "94307"
  },
  {
    "hot_word": "另一半向你借钱怎么办",
    "hot_word_num": "93955"
  },
  {
    "hot_word": "偶像要不要官宣恋情",
    "hot_word_num": "93633"
  },
  {
    "hot_word": "秦岚刘以豪告别太好哭了",
    "hot_word_num": "92582"
  },
  {
    "hot_word": "印度溃坝事件已致41人遇难",
    "hot_word_num": "82770"
  },
  {
    "hot_word": "百变大咖秀",
    "hot_word_num": "80170"
  },
  {
    "hot_word": "鬼灭之刃第二季",
    "hot_word_num": "69505"
  },
  {
    "hot_word": "低卡年夜饭",
    "hot_word_num": "64288"
  },
  {
    "hot_word": "比特币",
    "hot_word_num": "62855"
  },
  {
    "hot_word": "佛首是2020年回归第100件流失文物",
    "hot_word_num": "61765"
  },
  {
    "hot_word": "李健把清华校训唱成歌",
    "hot_word_num": "61582"
  },
  {
    "hot_word": "唐人街探案",
    "hot_word_num": "58073"
  },
  {
    "hot_word": "天天向上",
    "hot_word_num": "52966"
  },
  {
    "hot_word": "瓶邪",
    "hot_word_num": "48404"
  },
  {
    "hot_word": "肖战说作品是演员立足的根本之道",
    "hot_word_num": "45583"
  },
  {
    "hot_word": "王俊凯情人节自拍",
    "hot_word_num": "43721"
  },
  {
    "hot_word": "你好李焕英",
    "hot_word_num": "43667"
  },
  {
    "hot_word": "情人节",
    "hot_word_num": "43287"
  },
  {
    "hot_word": "霍思燕说春晚的牛好像杜江",
    "hot_word_num": "42545"
  },
  {
    "hot_word": "95后小伙在铅笔芯上刻出一头牛",
    "hot_word_num": "42433"
  },
  {
    "hot_word": "杨蒙恩吐槽张大大",
    "hot_word_num": "42374"
  },
  {
    "hot_word": "唐仁 人设",
    "hot_word_num": "40582"
  },
  {
    "hot_word": "女婿跟老丈人告状",
    "hot_word_num": "39697"
  },
  {
    "hot_word": "人潮汹涌台词",
    "hot_word_num": "39053"
  },
  {
    "hot_word": "玫瑰花",
    "hot_word_num": "38969"
  },
  {
    "hot_word": "唐探3细节",
    "hot_word_num": "35130"
  },
  {
    "hot_word": "海拔5200米高原上的婚礼",
    "hot_word_num": "34804"
  },
  {
    "hot_word": "4AM12杀吃鸡",
    "hot_word_num": "33100"
  },
  {
    "hot_word": "贝佐斯重返全球首富宝座",
    "hot_word_num": "32665"
  },
  {
    "hot_word": "德国博物馆藏品中发现北宋汝窑瓷器",
    "hot_word_num": "30797"
  },
  {
    "hot_word": "刺杀小说家",
    "hot_word_num": "30516"
  }
]
