[
  {
    "hot_word": "冯绍峰 细手腕和细脚腕终于被发现了",
    "hot_word_num": "1923739"
  },
  {
    "hot_word": "疫苗接种证明不能代替核酸检测报告",
    "hot_word_num": "1734728"
  },
  {
    "hot_word": "科颜氏170周年",
    "hot_word_num": "1716132"
  },
  {
    "hot_word": "井柏然 杨紫从小妹妹变成大妹妹了",
    "hot_word_num": "1618499"
  },
  {
    "hot_word": "专家称王俊凯泡脚方式是无效养生",
    "hot_word_num": "1447651"
  },
  {
    "hot_word": "当我看到男友和兄弟的对话",
    "hot_word_num": "1085718"
  },
  {
    "hot_word": "可口可乐将涨价",
    "hot_word_num": "839842"
  },
  {
    "hot_word": "韩国学生削发抗议日本核污水入海",
    "hot_word_num": "644231"
  },
  {
    "hot_word": "中国国画院20套违建别墅被没收",
    "hot_word_num": "548912"
  },
  {
    "hot_word": "调戏女子并追砍其丈夫男子被刑拘",
    "hot_word_num": "493983"
  },
  {
    "hot_word": "张柏芝 我的新名字张百知",
    "hot_word_num": "490697"
  },
  {
    "hot_word": "井柏然 我现在爱的是李荣浩",
    "hot_word_num": "488812"
  },
  {
    "hot_word": "张雨绮丁程鑫加入快乐大本营",
    "hot_word_num": "483704"
  },
  {
    "hot_word": "中央政法委评特斯拉车展维权",
    "hot_word_num": "481524"
  },
  {
    "hot_word": "食堂师傅曾资助中科院走红博士",
    "hot_word_num": "477376"
  },
  {
    "hot_word": "工信部今年组织下架107款拒不整改APP",
    "hot_word_num": "472234"
  },
  {
    "hot_word": "关晓彤父母公司新增行政处罚",
    "hot_word_num": "470178"
  },
  {
    "hot_word": "雪碧拌面",
    "hot_word_num": "464659"
  },
  {
    "hot_word": "干细胞注射竟长出牙槽骨",
    "hot_word_num": "460419"
  },
  {
    "hot_word": "就医时令人窒息的社死瞬间",
    "hot_word_num": "460379"
  },
  {
    "hot_word": "北京草莓音乐节阵容",
    "hot_word_num": "436098"
  },
  {
    "hot_word": "在宿舍演出了大片的感觉",
    "hot_word_num": "407508"
  },
  {
    "hot_word": "青春环游记3拟邀嘉宾",
    "hot_word_num": "406048"
  },
  {
    "hot_word": "拍照时一定要把腿并好",
    "hot_word_num": "392118"
  },
  {
    "hot_word": "肖战 小面包又来害我了",
    "hot_word_num": "310938"
  },
  {
    "hot_word": "吴昕问周柯宇是不是又长高了",
    "hot_word_num": "302964"
  },
  {
    "hot_word": "范丞丞学院风游客照",
    "hot_word_num": "302220"
  },
  {
    "hot_word": "董明珠谈格力接班人",
    "hot_word_num": "301167"
  },
  {
    "hot_word": "非法集资公司女出纳挪用1600多万",
    "hot_word_num": "300911"
  },
  {
    "hot_word": "做胃镜到底有多痛苦",
    "hot_word_num": "300816"
  },
  {
    "hot_word": "我真是大明星官宣",
    "hot_word_num": "284823"
  },
  {
    "hot_word": "3000万剂疫苗在美国仓库里吃灰",
    "hot_word_num": "267685"
  },
  {
    "hot_word": "日本复兴相为氚吉祥物低头致歉",
    "hot_word_num": "229129"
  },
  {
    "hot_word": "鬼屋里最恐怖的事",
    "hot_word_num": "223289"
  },
  {
    "hot_word": "新疆的小学什么样",
    "hot_word_num": "215847"
  },
  {
    "hot_word": "赵露思起诉黑粉",
    "hot_word_num": "210339"
  },
  {
    "hot_word": "关晓彤",
    "hot_word_num": "208591"
  },
  {
    "hot_word": "老人边看英文版高数边卖鸡蛋",
    "hot_word_num": "198129"
  },
  {
    "hot_word": "乃万发88红包请宋妍霏出演MV",
    "hot_word_num": "192937"
  },
  {
    "hot_word": "迪丽热巴给吴磊整理头发",
    "hot_word_num": "184893"
  },
  {
    "hot_word": "济南拟对遗弃犬只罚款2000元",
    "hot_word_num": "174242"
  },
  {
    "hot_word": "山河令",
    "hot_word_num": "136570"
  },
  {
    "hot_word": "每个人上学时都有的经历",
    "hot_word_num": "122241"
  },
  {
    "hot_word": "外交部 日本核污水和正常排水本质不同",
    "hot_word_num": "117886"
  },
  {
    "hot_word": "乍得总统在前线受重伤死亡",
    "hot_word_num": "117492"
  },
  {
    "hot_word": "阴阳师帝释天",
    "hot_word_num": "117434"
  },
  {
    "hot_word": "爸爸是浪漫第一名",
    "hot_word_num": "117222"
  },
  {
    "hot_word": "济南拟规定每户居民仅养1只小型犬",
    "hot_word_num": "116114"
  },
  {
    "hot_word": "黑龙江省考成绩",
    "hot_word_num": "115601"
  },
  {
    "hot_word": "林郑月娥说要让香港人更有国民意识",
    "hot_word_num": "115120"
  }
]
