[
  {
    "hot_word": "赵紫薇发与孟子义聊天截图",
    "hot_word_num": "4987810"
  },
  {
    "hot_word": "美国新冠死亡数相当于每天掉两架客机",
    "hot_word_num": "2778342"
  },
  {
    "hot_word": "于正朋友圈发文",
    "hot_word_num": "1828266"
  },
  {
    "hot_word": "邓超吐槽陪孙俪选窗帘意见全被否定",
    "hot_word_num": "1495283"
  },
  {
    "hot_word": "河南原阳一农家6人被杀",
    "hot_word_num": "1493131"
  },
  {
    "hot_word": "找不到工作的原因找到了",
    "hot_word_num": "1481554"
  },
  {
    "hot_word": "马保国回应被恶搞",
    "hot_word_num": "1472809"
  },
  {
    "hot_word": "钟南山疫情期间日程表",
    "hot_word_num": "1464364"
  },
  {
    "hot_word": "纽约州回应白宫不提供新冠疫苗",
    "hot_word_num": "1459572"
  },
  {
    "hot_word": "抗糖真能抗衰老吗",
    "hot_word_num": "1456075"
  },
  {
    "hot_word": "王耀庆老师 桃李满天下",
    "hot_word_num": "1448714"
  },
  {
    "hot_word": "丁程鑫发长文",
    "hot_word_num": "1159258"
  },
  {
    "hot_word": "张一山版韦小宝",
    "hot_word_num": "960251"
  },
  {
    "hot_word": "用排球砸学生体育老师已停课",
    "hot_word_num": "876929"
  },
  {
    "hot_word": "护士带214斤孕妇跳摇摆舞助产",
    "hot_word_num": "851545"
  },
  {
    "hot_word": "当蛋糕师没有感情时",
    "hot_word_num": "849761"
  },
  {
    "hot_word": "丁真直播",
    "hot_word_num": "812698"
  },
  {
    "hot_word": "孟子义回应陈情令片场失火",
    "hot_word_num": "659644"
  },
  {
    "hot_word": "以色列公司推出无耳机传输音乐",
    "hot_word_num": "556610"
  },
  {
    "hot_word": "鸡胸肉脆片",
    "hot_word_num": "486508"
  },
  {
    "hot_word": "王一博晒玩滑板视频",
    "hot_word_num": "471168"
  },
  {
    "hot_word": "齐溪夸杨紫演技",
    "hot_word_num": "454472"
  },
  {
    "hot_word": "哈利波特主演隔空重聚",
    "hot_word_num": "444978"
  },
  {
    "hot_word": "蔡少芬儿子小名",
    "hot_word_num": "376617"
  },
  {
    "hot_word": "潘玮柏吴克群合影姿势",
    "hot_word_num": "374572"
  },
  {
    "hot_word": "刘雨昕紫色西装",
    "hot_word_num": "364101"
  },
  {
    "hot_word": "加油体测人",
    "hot_word_num": "351222"
  },
  {
    "hot_word": "RCEP正式签署",
    "hot_word_num": "314047"
  },
  {
    "hot_word": "体育课可选修舞龙舞狮",
    "hot_word_num": "292198"
  },
  {
    "hot_word": "天空之镜变身天鹅湖",
    "hot_word_num": "290386"
  },
  {
    "hot_word": "白敬亭英文名叫GoodBai",
    "hot_word_num": "290156"
  },
  {
    "hot_word": "这样的友情真的存在吗",
    "hot_word_num": "288641"
  },
  {
    "hot_word": "10年前的英雄联盟",
    "hot_word_num": "279356"
  },
  {
    "hot_word": "拜登获306张选举人票特朗普获232张",
    "hot_word_num": "259161"
  },
  {
    "hot_word": "邓伦杭州",
    "hot_word_num": "255116"
  },
  {
    "hot_word": "陈坤跑步好可爱",
    "hot_word_num": "253467"
  },
  {
    "hot_word": "白岩松谈医生术后喝葡萄糖水争议",
    "hot_word_num": "248721"
  },
  {
    "hot_word": "人数不够备注来凑",
    "hot_word_num": "212129"
  },
  {
    "hot_word": "珉豪戴着口罩吹蜡烛",
    "hot_word_num": "209928"
  },
  {
    "hot_word": "女生为了取快递有多拼",
    "hot_word_num": "197482"
  },
  {
    "hot_word": "灵超机场视频",
    "hot_word_num": "188671"
  },
  {
    "hot_word": "优胜教育初步统计补偿2万余人",
    "hot_word_num": "182944"
  },
  {
    "hot_word": "买过最有仪式感的巧克力",
    "hot_word_num": "171831"
  },
  {
    "hot_word": "中日首次达成双边关税减让安排",
    "hot_word_num": "167078"
  },
  {
    "hot_word": "画皮原导演点评郭敬明改编",
    "hot_word_num": "155248"
  },
  {
    "hot_word": "易烊千玺时尚COSMO封面预告",
    "hot_word_num": "134090"
  },
  {
    "hot_word": "章丘大葱破世界吉尼斯葱高纪录",
    "hot_word_num": "123037"
  },
  {
    "hot_word": "和平精英世界冠军",
    "hot_word_num": "108796"
  },
  {
    "hot_word": "美国疫情",
    "hot_word_num": "108503"
  },
  {
    "hot_word": "兵哥哥60分钟徒手仰卧起坐1457个",
    "hot_word_num": "95655"
  }
]
