[
  {
    "hot_word": "关晓彤陈飞宇对称表情",
    "hot_word_num": "4567183"
  },
  {
    "hot_word": "官方通报举报补课被班主任丈夫暴打",
    "hot_word_num": "3315609"
  },
  {
    "hot_word": "所以贾玲见到刘德华了吗",
    "hot_word_num": "2460488"
  },
  {
    "hot_word": "周冬雨金鸡奖最佳女主角",
    "hot_word_num": "2289341"
  },
  {
    "hot_word": "我们离婚了",
    "hot_word_num": "1963443"
  },
  {
    "hot_word": "西藏和四川开始rap battle了",
    "hot_word_num": "1926251"
  },
  {
    "hot_word": "快乐大本营",
    "hot_word_num": "1890242"
  },
  {
    "hot_word": "隐秘而伟大大结局",
    "hot_word_num": "1846584"
  },
  {
    "hot_word": "国务院建议试行企业休眠制度",
    "hot_word_num": "1834282"
  },
  {
    "hot_word": "演员请就位",
    "hot_word_num": "1765012"
  },
  {
    "hot_word": "黄晓明金鸡奖最佳男主角",
    "hot_word_num": "1748139"
  },
  {
    "hot_word": "尔冬升离场",
    "hot_word_num": "1723478"
  },
  {
    "hot_word": "狼殿下",
    "hot_word_num": "1665025"
  },
  {
    "hot_word": "陕西2地店家急寻顾客做核酸检测",
    "hot_word_num": "1664088"
  },
  {
    "hot_word": "郭敬明被尔冬升怼哭",
    "hot_word_num": "1663469"
  },
  {
    "hot_word": "刘德华 可能明年金鸡奖有我提名",
    "hot_word_num": "1225530"
  },
  {
    "hot_word": "广东一18岁高中生迎娶14岁初中生",
    "hot_word_num": "1155988"
  },
  {
    "hot_word": "甘孜机票预定量",
    "hot_word_num": "934221"
  },
  {
    "hot_word": "高校寒假时间",
    "hot_word_num": "922860"
  },
  {
    "hot_word": "周冬雨金马金像金鸡三金影后",
    "hot_word_num": "914016"
  },
  {
    "hot_word": "印小天金鸡奖最佳男配角",
    "hot_word_num": "759684"
  },
  {
    "hot_word": "绿松石耳坠",
    "hot_word_num": "753148"
  },
  {
    "hot_word": "西安年底前禁用不可降解塑料袋",
    "hot_word_num": "750012"
  },
  {
    "hot_word": "小胖哭了",
    "hot_word_num": "743514"
  },
  {
    "hot_word": "金鸡奖红毯",
    "hot_word_num": "732532"
  },
  {
    "hot_word": "丁真肤色跟热干面挺像的",
    "hot_word_num": "729773"
  },
  {
    "hot_word": "东风快递后来的我们",
    "hot_word_num": "674354"
  },
  {
    "hot_word": "嫦娥五号踩了脚太空刹车",
    "hot_word_num": "658116"
  },
  {
    "hot_word": "伊朗称以色列参与暗杀核科学家",
    "hot_word_num": "646605"
  },
  {
    "hot_word": "袁泉金鸡奖最佳女配角",
    "hot_word_num": "643351"
  },
  {
    "hot_word": "中山大学副教授否认燕窝是智商税",
    "hot_word_num": "496183"
  },
  {
    "hot_word": "李佳琦直播",
    "hot_word_num": "464145"
  },
  {
    "hot_word": "丁程鑫画心好唯美",
    "hot_word_num": "431389"
  },
  {
    "hot_word": "2021年起我国将全面禁止进口固体废物",
    "hot_word_num": "421357"
  },
  {
    "hot_word": "高以翔女友晒合照悼念",
    "hot_word_num": "419321"
  },
  {
    "hot_word": "沈腾骑自行车走红毯",
    "hot_word_num": "404335"
  },
  {
    "hot_word": "夏处长没有牺牲",
    "hot_word_num": "365925"
  },
  {
    "hot_word": "金鸡奖最佳音乐奖空缺",
    "hot_word_num": "360338"
  },
  {
    "hot_word": "持刀凶徒在干警追逃下窜入法院",
    "hot_word_num": "360327"
  },
  {
    "hot_word": "宋亚轩全开麦",
    "hot_word_num": "360326"
  },
  {
    "hot_word": "秦岭地下1840米施工现场",
    "hot_word_num": "350663"
  },
  {
    "hot_word": "搭讪路人偷拍上传涉嫌违法",
    "hot_word_num": "349636"
  },
  {
    "hot_word": "时代少年团演唱会",
    "hot_word_num": "349279"
  },
  {
    "hot_word": "嫦娥五号顺利进入环月轨道",
    "hot_word_num": "306773"
  },
  {
    "hot_word": "谢娜为易烊千玺庆生",
    "hot_word_num": "301669"
  },
  {
    "hot_word": "如意芳霏",
    "hot_word_num": "229461"
  },
  {
    "hot_word": "道枝骏佑 创4",
    "hot_word_num": "219410"
  },
  {
    "hot_word": "虐杀动物兜售视频成地下产业链",
    "hot_word_num": "202264"
  },
  {
    "hot_word": "李易峰演技",
    "hot_word_num": "201483"
  },
  {
    "hot_word": "马嘉祺严浩翔合唱飘向北方",
    "hot_word_num": "196378"
  }
]
