[
  {
    "hot_word": "胡一天给乔欣发12块2毛8分红包",
    "hot_word_num": "1810731"
  },
  {
    "hot_word": "心脏支架价格是怎么降下来的",
    "hot_word_num": "1427185"
  },
  {
    "hot_word": "羊驼朝朱一龙吐口水",
    "hot_word_num": "1332561"
  },
  {
    "hot_word": "黄之锋认罪",
    "hot_word_num": "953143"
  },
  {
    "hot_word": "马龙夺冠后眼眶红了",
    "hot_word_num": "804802"
  },
  {
    "hot_word": "郁可唯的隐藏技能",
    "hot_word_num": "775984"
  },
  {
    "hot_word": "张梓琳4岁女儿腿长",
    "hot_word_num": "767375"
  },
  {
    "hot_word": "不想上班",
    "hot_word_num": "727082"
  },
  {
    "hot_word": "特朗普称巴黎协定旨在扼杀美国经济",
    "hot_word_num": "718425"
  },
  {
    "hot_word": "美国护士哭诉同事接连成了自己的病人",
    "hot_word_num": "717428"
  },
  {
    "hot_word": "上海9日确诊病例曾暴露于一航空集装器",
    "hot_word_num": "560556"
  },
  {
    "hot_word": "请回答1988余晖扮演者白血病复发",
    "hot_word_num": "507183"
  },
  {
    "hot_word": "王大陆把李沁嘴巴亲变形了",
    "hot_word_num": "479949"
  },
  {
    "hot_word": "下雪",
    "hot_word_num": "454553"
  },
  {
    "hot_word": "胡先煦买的超多黄大闸蟹",
    "hot_word_num": "452864"
  },
  {
    "hot_word": "台南人是怎么过生日的",
    "hot_word_num": "450541"
  },
  {
    "hot_word": "罗云熙十年前素颜证件照",
    "hot_word_num": "448758"
  },
  {
    "hot_word": "武汉高校学生疑盗清华美术生作品参赛",
    "hot_word_num": "444468"
  },
  {
    "hot_word": "苹果掉出全球手机市场前三",
    "hot_word_num": "442095"
  },
  {
    "hot_word": "东北摊主用猪蹄辣条做糖葫芦",
    "hot_word_num": "439339"
  },
  {
    "hot_word": "菜市场的衣服真的绝了",
    "hot_word_num": "437541"
  },
  {
    "hot_word": "当程序员和程序员谈恋爱时",
    "hot_word_num": "434829"
  },
  {
    "hot_word": "周庭",
    "hot_word_num": "420709"
  },
  {
    "hot_word": "金珉锡退伍",
    "hot_word_num": "399487"
  },
  {
    "hot_word": "雪后西安秒变长安",
    "hot_word_num": "387447"
  },
  {
    "hot_word": "乔欣深秋落叶大片",
    "hot_word_num": "385147"
  },
  {
    "hot_word": "基金",
    "hot_word_num": "345380"
  },
  {
    "hot_word": "阿联酋新发现石油",
    "hot_word_num": "344597"
  },
  {
    "hot_word": "改革开放以来中国7亿多人摆脱贫困",
    "hot_word_num": "344495"
  },
  {
    "hot_word": "原来鹅也喜欢撸猫",
    "hot_word_num": "344452"
  },
  {
    "hot_word": "奔跑吧黄河定档",
    "hot_word_num": "317917"
  },
  {
    "hot_word": "村民在放生现场抄网捞鱼",
    "hot_word_num": "291094"
  },
  {
    "hot_word": "明星早期青涩照",
    "hot_word_num": "283088"
  },
  {
    "hot_word": "特朗普竞选总部要求再次重新计票",
    "hot_word_num": "267284"
  },
  {
    "hot_word": "给妈妈写的零花钱申请书",
    "hot_word_num": "261283"
  },
  {
    "hot_word": "当别人拿我手机时",
    "hot_word_num": "255819"
  },
  {
    "hot_word": "白宇 我站在永宁门想着你",
    "hot_word_num": "204879"
  },
  {
    "hot_word": "温碧霞有意向参加浪姐2",
    "hot_word_num": "200546"
  },
  {
    "hot_word": "浦东机场高风险岗位新冠疫苗应急接种",
    "hot_word_num": "200292"
  },
  {
    "hot_word": "李若彤肌肉线条",
    "hot_word_num": "187489"
  },
  {
    "hot_word": "蛋壳",
    "hot_word_num": "187000"
  },
  {
    "hot_word": "美国7000人不戴口罩参加婚礼",
    "hot_word_num": "185945"
  },
  {
    "hot_word": "海关检查货车发现140张麝鼠皮",
    "hot_word_num": "158588"
  },
  {
    "hot_word": "冰桶挑战联合发起人奎恩去世",
    "hot_word_num": "153595"
  },
  {
    "hot_word": "原神",
    "hot_word_num": "146569"
  },
  {
    "hot_word": "微信新表情的正确打开方式",
    "hot_word_num": "136143"
  },
  {
    "hot_word": "浦东机场所有相关工作人员连夜核酸检测",
    "hot_word_num": "133459"
  },
  {
    "hot_word": "学校回应家长为避雨遭保安赶出",
    "hot_word_num": "125016"
  },
  {
    "hot_word": "8年前航母style走红",
    "hot_word_num": "123702"
  },
  {
    "hot_word": "特斯拉回应车辆行驶中天窗脱落",
    "hot_word_num": "123490"
  }
]
