[
  {
    "hot_word": "郑爽涉嫌签订阴阳合同被调查",
    "hot_word_num": "6308926"
  },
  {
    "hot_word": "女子取快递被造谣出轨案30日将开庭",
    "hot_word_num": "2984579"
  },
  {
    "hot_word": "张若昀正式起诉父亲张健",
    "hot_word_num": "2731015"
  },
  {
    "hot_word": "张翰吃牛肉面了",
    "hot_word_num": "1932181"
  },
  {
    "hot_word": "普通话二级甲等的猫咪",
    "hot_word_num": "1163539"
  },
  {
    "hot_word": "王力宏即兴创作新歌",
    "hot_word_num": "1156098"
  },
  {
    "hot_word": "赵立坚回应转发网友画作",
    "hot_word_num": "791451"
  },
  {
    "hot_word": "贵阳机场回应厕所洗手台上布满化石",
    "hot_word_num": "763685"
  },
  {
    "hot_word": "86岁科学家凌晨4点开始工作",
    "hot_word_num": "500209"
  },
  {
    "hot_word": "李菲儿说不认识Angelababy",
    "hot_word_num": "494929"
  },
  {
    "hot_word": "陈建斌 蒋勤勤出门是史诗级长篇连续剧",
    "hot_word_num": "494305"
  },
  {
    "hot_word": "推文被日方抗议后赵立坚索性将其置顶了",
    "hot_word_num": "489307"
  },
  {
    "hot_word": "游客农家乐遭强奸已被警方立案",
    "hot_word_num": "488878"
  },
  {
    "hot_word": "5月1日起调整部分钢铁产品关税",
    "hot_word_num": "486703"
  },
  {
    "hot_word": "张翰十年只谈过两个女朋友",
    "hot_word_num": "481353"
  },
  {
    "hot_word": "五一假期全面实施门票预约制度",
    "hot_word_num": "420678"
  },
  {
    "hot_word": "孙燕姿肖战互关",
    "hot_word_num": "417758"
  },
  {
    "hot_word": "闲鱼崩了",
    "hot_word_num": "416429"
  },
  {
    "hot_word": "苹果将削减AirPods的产量",
    "hot_word_num": "412047"
  },
  {
    "hot_word": "2021湖南卫视大剧片单",
    "hot_word_num": "409063"
  },
  {
    "hot_word": "甘望星回应撞脸宋威龙",
    "hot_word_num": "406249"
  },
  {
    "hot_word": "吴宣仪 我感情洁癖",
    "hot_word_num": "401094"
  },
  {
    "hot_word": "肖战给孙燕姿反黑",
    "hot_word_num": "398695"
  },
  {
    "hot_word": "阿娇胖了",
    "hot_word_num": "395396"
  },
  {
    "hot_word": "王嘉尔蓝色真空马甲",
    "hot_word_num": "393064"
  },
  {
    "hot_word": "英雄联盟修改英雄称号",
    "hot_word_num": "383444"
  },
  {
    "hot_word": "没有武林外传蹭不上的热点",
    "hot_word_num": "378061"
  },
  {
    "hot_word": "美团回应副处长当骑手1天赚41块",
    "hot_word_num": "327318"
  },
  {
    "hot_word": "狗狗币大涨",
    "hot_word_num": "289107"
  },
  {
    "hot_word": "泰式奶茶浓颜妆",
    "hot_word_num": "286761"
  },
  {
    "hot_word": "脑子和四肢各干各的",
    "hot_word_num": "268696"
  },
  {
    "hot_word": "男子15万8卖亲儿子后到处挥霍",
    "hot_word_num": "260369"
  },
  {
    "hot_word": "90岁结核医生说最有效的处方是爱",
    "hot_word_num": "238846"
  },
  {
    "hot_word": "从楼上明白了分手的痛苦",
    "hot_word_num": "234002"
  },
  {
    "hot_word": "怦然心动20岁艺人官宣",
    "hot_word_num": "229472"
  },
  {
    "hot_word": "工作沟通发语音好还是发文字好",
    "hot_word_num": "222245"
  },
  {
    "hot_word": "我国人造卫星开拓者闵桂荣院士逝世",
    "hot_word_num": "207937"
  },
  {
    "hot_word": "现在的家长有多硬核",
    "hot_word_num": "198172"
  },
  {
    "hot_word": "大岛日记",
    "hot_word_num": "189285"
  },
  {
    "hot_word": "小舍得",
    "hot_word_num": "183375"
  },
  {
    "hot_word": "上海一高校期末考当堂办婚礼",
    "hot_word_num": "172325"
  },
  {
    "hot_word": "央视揭秘赚钱类App套路",
    "hot_word_num": "172209"
  },
  {
    "hot_word": "金莎 求姻缘结果求到了状元签",
    "hot_word_num": "171538"
  },
  {
    "hot_word": "海口救触电小学生的是70岁退休医生",
    "hot_word_num": "170517"
  },
  {
    "hot_word": "长歌行",
    "hot_word_num": "170401"
  },
  {
    "hot_word": "你的婚礼",
    "hot_word_num": "169877"
  },
  {
    "hot_word": "男子车展长时间操作中控被骂",
    "hot_word_num": "167772"
  },
  {
    "hot_word": "从经济学角度看调休",
    "hot_word_num": "167515"
  },
  {
    "hot_word": "印度变种病毒至少已在17国出现",
    "hot_word_num": "167494"
  },
  {
    "hot_word": "国台办回应两岸最终难免一战说法",
    "hot_word_num": "166693"
  }
]
