[
  {
    "hot_word": "刘涛晒给老公王珂剃头照",
    "hot_word_num": "2016280"
  },
  {
    "hot_word": "特斯拉被五部门约谈",
    "hot_word_num": "1562520"
  },
  {
    "hot_word": "郑州茅台酒商签1499元承诺但拒售",
    "hot_word_num": "1238266"
  },
  {
    "hot_word": "沈腾说乔杉比女演员的脸都小",
    "hot_word_num": "1090384"
  },
  {
    "hot_word": "跷二郎腿的后果",
    "hot_word_num": "860417"
  },
  {
    "hot_word": "天猫发福啦",
    "hot_word_num": "830674"
  },
  {
    "hot_word": "内蒙古赤峰一批进口车厘子检测阳性",
    "hot_word_num": "819106"
  },
  {
    "hot_word": "我国科学家揭示阿尔茨海默症致病新机制",
    "hot_word_num": "674777"
  },
  {
    "hot_word": "春节离杭需退还1000元红包",
    "hot_word_num": "500772"
  },
  {
    "hot_word": "核酸阳性车厘子不一定具有传染性",
    "hot_word_num": "500324"
  },
  {
    "hot_word": "郝蕾前经纪人发声",
    "hot_word_num": "499031"
  },
  {
    "hot_word": "江西赣州一货车撞小轿车致6人死亡",
    "hot_word_num": "472508"
  },
  {
    "hot_word": "刘涛工作室辟谣",
    "hot_word_num": "391336"
  },
  {
    "hot_word": "加拿大承认文化衫冒犯中国公众",
    "hot_word_num": "370976"
  },
  {
    "hot_word": "我们女生就不要互相挑毛病了",
    "hot_word_num": "351453"
  },
  {
    "hot_word": "教育部严禁以任何形式公布高考状元",
    "hot_word_num": "349501"
  },
  {
    "hot_word": "lex",
    "hot_word_num": "347612"
  },
  {
    "hot_word": "宋轶邀郭麒麟拎包入赘",
    "hot_word_num": "343750"
  },
  {
    "hot_word": "关晓彤红衣挥鞭打戏",
    "hot_word_num": "342401"
  },
  {
    "hot_word": "赵今麦胶片写真",
    "hot_word_num": "338041"
  },
  {
    "hot_word": "迪丽热巴自拍",
    "hot_word_num": "336360"
  },
  {
    "hot_word": "仓库工人用牙刷写春联",
    "hot_word_num": "333937"
  },
  {
    "hot_word": "上海交大3名本科生被勒令退学",
    "hot_word_num": "330914"
  },
  {
    "hot_word": "合成大西瓜",
    "hot_word_num": "327224"
  },
  {
    "hot_word": "初恋脸女生图鉴",
    "hot_word_num": "325226"
  },
  {
    "hot_word": "美超级碗或变超级传播事件",
    "hot_word_num": "322305"
  },
  {
    "hot_word": "等等小花给邓超画生日快乐",
    "hot_word_num": "319955"
  },
  {
    "hot_word": "比特币",
    "hot_word_num": "316827"
  },
  {
    "hot_word": "外交部回应澳籍记者成蕾被逮捕",
    "hot_word_num": "311453"
  },
  {
    "hot_word": "中国富裕家庭数量首次突破500万户",
    "hot_word_num": "308839"
  },
  {
    "hot_word": "刘宇宁直播",
    "hot_word_num": "305462"
  },
  {
    "hot_word": "妈妈坚持4年为孩子做诗词早餐",
    "hot_word_num": "305305"
  },
  {
    "hot_word": "湖北宜昌一河道现大量现金",
    "hot_word_num": "302232"
  },
  {
    "hot_word": "最新百家姓排名",
    "hot_word_num": "293647"
  },
  {
    "hot_word": "假日暖洋洋大结局",
    "hot_word_num": "288128"
  },
  {
    "hot_word": "风起霓裳",
    "hot_word_num": "279652"
  },
  {
    "hot_word": "袁咏仪庆与张智霖结婚20周年",
    "hot_word_num": "277106"
  },
  {
    "hot_word": "幸福到万家杀青",
    "hot_word_num": "263568"
  },
  {
    "hot_word": "公司用1000万现金举办数钱比赛",
    "hot_word_num": "247423"
  },
  {
    "hot_word": "为什么不能轻易跟别人诉苦",
    "hot_word_num": "225060"
  },
  {
    "hot_word": "我就是这般女子",
    "hot_word_num": "222676"
  },
  {
    "hot_word": "金鱼馄饨包法",
    "hot_word_num": "210705"
  },
  {
    "hot_word": "教育部严厉打击高考移民",
    "hot_word_num": "204247"
  },
  {
    "hot_word": "两只小羊能有什么烦恼",
    "hot_word_num": "199573"
  },
  {
    "hot_word": "西安78岁奶奶街头给游客画扇面",
    "hot_word_num": "183143"
  },
  {
    "hot_word": "马金瑜再发声",
    "hot_word_num": "174326"
  },
  {
    "hot_word": "薇娅直播",
    "hot_word_num": "172306"
  },
  {
    "hot_word": "男高中生在女厕安监控威胁女生",
    "hot_word_num": "164461"
  },
  {
    "hot_word": "爸爸为10岁儿子买玩具拍连续剧",
    "hot_word_num": "155606"
  },
  {
    "hot_word": "累丑",
    "hot_word_num": "154628"
  }
]
