[
  {
    "hot_word": "东京饮用水致癌物严重超标",
    "hot_word_num": "2543969"
  },
  {
    "hot_word": "皓嫣大婚",
    "hot_word_num": "1562097"
  },
  {
    "hot_word": "小舍得大结局",
    "hot_word_num": "1365801"
  },
  {
    "hot_word": "利路修 重庆哪里可以散步",
    "hot_word_num": "1027916"
  },
  {
    "hot_word": "九岁时警察父亲牺牲现在他成了警察",
    "hot_word_num": "981477"
  },
  {
    "hot_word": "阿娇回应永不再婚",
    "hot_word_num": "873581"
  },
  {
    "hot_word": "张哲瀚全开麦",
    "hot_word_num": "761776"
  },
  {
    "hot_word": "男子因航班延误大闹机舱致再次延误",
    "hot_word_num": "699729"
  },
  {
    "hot_word": "菲律宾总统接种中国新冠疫苗",
    "hot_word_num": "657489"
  },
  {
    "hot_word": "相扑选手10秒被撂倒头砸地致死",
    "hot_word_num": "642642"
  },
  {
    "hot_word": "吴永恩 你别碰她脚",
    "hot_word_num": "633067"
  },
  {
    "hot_word": "山河令演唱会",
    "hot_word_num": "632362"
  },
  {
    "hot_word": "吴磊 小心隔墙有隼",
    "hot_word_num": "631982"
  },
  {
    "hot_word": "澳大利亚总理回应禁止在印度国民回国",
    "hot_word_num": "630813"
  },
  {
    "hot_word": "宋茜张佳宁王者闺蜜局",
    "hot_word_num": "630734"
  },
  {
    "hot_word": "长歌行",
    "hot_word_num": "630417"
  },
  {
    "hot_word": "鞠婧祎颜值",
    "hot_word_num": "629753"
  },
  {
    "hot_word": "韩国史上最长做空禁令解除",
    "hot_word_num": "628657"
  },
  {
    "hot_word": "山东健康码金色皮肤",
    "hot_word_num": "628106"
  },
  {
    "hot_word": "水蚁",
    "hot_word_num": "627028"
  },
  {
    "hot_word": "结婚时妈妈对女婿的叮嘱",
    "hot_word_num": "626723"
  },
  {
    "hot_word": "谢娜晒自己做的家常菜",
    "hot_word_num": "625760"
  },
  {
    "hot_word": "医生景区救人获终身免门票",
    "hot_word_num": "624906"
  },
  {
    "hot_word": "少林寺内竹林被上百游客刻字",
    "hot_word_num": "624432"
  },
  {
    "hot_word": "艺考之神张新成",
    "hot_word_num": "623863"
  },
  {
    "hot_word": "王嘉尔 国潮音乐节",
    "hot_word_num": "507838"
  },
  {
    "hot_word": "巨型龙卷风扑岸而来游客逃散",
    "hot_word_num": "502487"
  },
  {
    "hot_word": "NBA球队老板力顶狗狗币",
    "hot_word_num": "502092"
  },
  {
    "hot_word": "姚明说CBA要给年轻球员机会",
    "hot_word_num": "502035"
  },
  {
    "hot_word": "青你3巨幕",
    "hot_word_num": "502017"
  },
  {
    "hot_word": "当温柔的人突然冷漠时",
    "hot_word_num": "482230"
  },
  {
    "hot_word": "王嘉尔八首连唱",
    "hot_word_num": "462499"
  },
  {
    "hot_word": "山河令见面会",
    "hot_word_num": "405190"
  },
  {
    "hot_word": "小蜂猴被救时来了个空中大劈叉",
    "hot_word_num": "350495"
  },
  {
    "hot_word": "王鸥羊腿袖深V礼服",
    "hot_word_num": "330532"
  },
  {
    "hot_word": "厕所殴打孩子幼师被拘15日罚款500",
    "hot_word_num": "319000"
  },
  {
    "hot_word": "奥迪撞上隔离带腾空飞起4人受轻伤",
    "hot_word_num": "265580"
  },
  {
    "hot_word": "王俊凯唱少年",
    "hot_word_num": "261688"
  },
  {
    "hot_word": "金婚爷爷在孙辈婚礼上的致辞",
    "hot_word_num": "258746"
  },
  {
    "hot_word": "黄奕带女儿爬长城",
    "hot_word_num": "258632"
  },
  {
    "hot_word": "王俊凯灰色西装",
    "hot_word_num": "234521"
  },
  {
    "hot_word": "首都机场回应延误",
    "hot_word_num": "229061"
  },
  {
    "hot_word": "随手拍藏羚羊迁徙产仔",
    "hot_word_num": "227834"
  },
  {
    "hot_word": "发现自己正在衰老的迹象",
    "hot_word_num": "227659"
  },
  {
    "hot_word": "我是什么样子中国就是什么样子",
    "hot_word_num": "196901"
  },
  {
    "hot_word": "首都机场取消航班19架次",
    "hot_word_num": "180439"
  },
  {
    "hot_word": "李龙大感染新冠",
    "hot_word_num": "168414"
  },
  {
    "hot_word": "广州城战胜青岛",
    "hot_word_num": "162127"
  },
  {
    "hot_word": "北京大兴机场取消航班38架次",
    "hot_word_num": "161164"
  },
  {
    "hot_word": "多国对印度发出禁入令",
    "hot_word_num": "160675"
  }
]
