[
  {
    "hot_word": "哈尔滨性侵4岁女童嫌犯被判死刑",
    "hot_word_num": "2853775"
  },
  {
    "hot_word": "不准以任何方式强迫毕业生签就业协议",
    "hot_word_num": "2476022"
  },
  {
    "hot_word": "有道词典笔快快快快快快",
    "hot_word_num": "2365806"
  },
  {
    "hot_word": "林更新怼打一星的网友",
    "hot_word_num": "2151855"
  },
  {
    "hot_word": "金晨和陈一鸣约会害羞了",
    "hot_word_num": "1371987"
  },
  {
    "hot_word": "世界只剩中国FAST一只天眼",
    "hot_word_num": "1308163"
  },
  {
    "hot_word": "耿斯汉表白金莎",
    "hot_word_num": "977421"
  },
  {
    "hot_word": "澳大利亚",
    "hot_word_num": "910805"
  },
  {
    "hot_word": "阿富汗时报发表社论",
    "hot_word_num": "779824"
  },
  {
    "hot_word": "湖南卫视跨年首波阵容",
    "hot_word_num": "769077"
  },
  {
    "hot_word": "胡一天扯乔欣衣服撒娇",
    "hot_word_num": "769045"
  },
  {
    "hot_word": "吴谨言洪尧",
    "hot_word_num": "738998"
  },
  {
    "hot_word": "舅舅介绍丁真走红经过",
    "hot_word_num": "733642"
  },
  {
    "hot_word": "满洲里东山街道办事处升为高风险地区",
    "hot_word_num": "713455"
  },
  {
    "hot_word": "上海业主招女性生活助理年薪百万",
    "hot_word_num": "703466"
  },
  {
    "hot_word": "如何温柔的提出分手",
    "hot_word_num": "694357"
  },
  {
    "hot_word": "罗志祥",
    "hot_word_num": "685109"
  },
  {
    "hot_word": "薇娅",
    "hot_word_num": "670290"
  },
  {
    "hot_word": "香奈儿发布虚假广告被罚款20万",
    "hot_word_num": "650326"
  },
  {
    "hot_word": "来自牙医的朋友圈哭诉",
    "hot_word_num": "647361"
  },
  {
    "hot_word": "这些微信表情默默消失了",
    "hot_word_num": "645867"
  },
  {
    "hot_word": "15岁女生发明捡乒乓球机器人",
    "hot_word_num": "549580"
  },
  {
    "hot_word": "何洛洛回应和女生玩密室",
    "hot_word_num": "475926"
  },
  {
    "hot_word": "邦邦竟然还表白冷冷",
    "hot_word_num": "429133"
  },
  {
    "hot_word": "张国立回复网友评论",
    "hot_word_num": "421986"
  },
  {
    "hot_word": "黄俊捷恋情",
    "hot_word_num": "386153"
  },
  {
    "hot_word": "学生成绩排名应该公开吗",
    "hot_word_num": "373200"
  },
  {
    "hot_word": "小米集团在香港暂停交易",
    "hot_word_num": "369138"
  },
  {
    "hot_word": "中国驻法国使馆发言人回应",
    "hot_word_num": "368744"
  },
  {
    "hot_word": "日本新冠疫苗接种费用由国家承担",
    "hot_word_num": "368641"
  },
  {
    "hot_word": "因为身高吃过的亏",
    "hot_word_num": "356757"
  },
  {
    "hot_word": "女儿们的恋爱",
    "hot_word_num": "348563"
  },
  {
    "hot_word": "唐僧的拉踩能力有多强",
    "hot_word_num": "288521"
  },
  {
    "hot_word": "华春莹回应泡菜问题",
    "hot_word_num": "283398"
  },
  {
    "hot_word": "这个师傅是属仓鼠的吧",
    "hot_word_num": "282584"
  },
  {
    "hot_word": "长岛冰茶碎花美甲",
    "hot_word_num": "253411"
  },
  {
    "hot_word": "我们恋爱吧",
    "hot_word_num": "200701"
  },
  {
    "hot_word": "电焊专业在寝室赶作业",
    "hot_word_num": "198832"
  },
  {
    "hot_word": "天津立法禁止采集人脸识别信息",
    "hot_word_num": "197328"
  },
  {
    "hot_word": "用直男思维打败直男",
    "hot_word_num": "196653"
  },
  {
    "hot_word": "国际乒联最新世界排名",
    "hot_word_num": "196470"
  },
  {
    "hot_word": "乌布雷求婚成功",
    "hot_word_num": "194064"
  },
  {
    "hot_word": "火箭签下考辛斯",
    "hot_word_num": "192564"
  },
  {
    "hot_word": "南方装地暖降价近半",
    "hot_word_num": "191998"
  },
  {
    "hot_word": "圣诞大战赛程",
    "hot_word_num": "190574"
  },
  {
    "hot_word": "冬天里的第一双鞋",
    "hot_word_num": "189360"
  },
  {
    "hot_word": "上海技能人才平均工资突破12万元",
    "hot_word_num": "186559"
  },
  {
    "hot_word": "吃个方便面太不容易了",
    "hot_word_num": "184860"
  },
  {
    "hot_word": "陈立农哈妮克孜直播",
    "hot_word_num": "179651"
  },
  {
    "hot_word": "黄子韬摘头盔",
    "hot_word_num": "179043"
  }
]
