[
  {
    "hot_word": "经纪人证实信已分手",
    "hot_word_num": "4563033"
  },
  {
    "hot_word": "机长身体不适降落后不治身亡",
    "hot_word_num": "1443911"
  },
  {
    "hot_word": "NI的圣诞购物车",
    "hot_word_num": "1417490"
  },
  {
    "hot_word": "何炅",
    "hot_word_num": "1393100"
  },
  {
    "hot_word": "钟南山说除了严防死守也要打疫苗",
    "hot_word_num": "1231303"
  },
  {
    "hot_word": "圣诞礼物能壕到什么程度",
    "hot_word_num": "1151080"
  },
  {
    "hot_word": "隐秘的角落入围全球15部最佳剧集",
    "hot_word_num": "1113327"
  },
  {
    "hot_word": "浙江发现无症状感染者详情",
    "hot_word_num": "1085296"
  },
  {
    "hot_word": "沈阳宣布进入战时状态",
    "hot_word_num": "962982"
  },
  {
    "hot_word": "赵立坚说中国彰显在南海海上的责任担当",
    "hot_word_num": "962285"
  },
  {
    "hot_word": "元旦起上海超市禁止提供塑料袋",
    "hot_word_num": "961579"
  },
  {
    "hot_word": "吴昕出售粉丝送的HelloKitty水晶",
    "hot_word_num": "959900"
  },
  {
    "hot_word": "一直以为周迅是单身",
    "hot_word_num": "958671"
  },
  {
    "hot_word": "杜海涛",
    "hot_word_num": "956322"
  },
  {
    "hot_word": "淫秽漫画作者JM被刑拘",
    "hot_word_num": "956043"
  },
  {
    "hot_word": "郑渊洁曾买10套房放读者写的信",
    "hot_word_num": "918202"
  },
  {
    "hot_word": "小风暴",
    "hot_word_num": "900141"
  },
  {
    "hot_word": "武艺晒快本送的礼物后秒删",
    "hot_word_num": "898912"
  },
  {
    "hot_word": "花呗调整年轻用户额度",
    "hot_word_num": "892371"
  },
  {
    "hot_word": "租房压力最大的10大城市",
    "hot_word_num": "745209"
  },
  {
    "hot_word": "快乐家族",
    "hot_word_num": "713154"
  },
  {
    "hot_word": "王安宇范丞丞打架路透",
    "hot_word_num": "660173"
  },
  {
    "hot_word": "高圣远称和周迅没有财产问题",
    "hot_word_num": "599848"
  },
  {
    "hot_word": "朱时茂曾发博怼快乐大本营",
    "hot_word_num": "538183"
  },
  {
    "hot_word": "尹正胖出双下巴",
    "hot_word_num": "525097"
  },
  {
    "hot_word": "金莎 我想要赌一赌真正的爱情",
    "hot_word_num": "475747"
  },
  {
    "hot_word": "宁波无症状感染者系考研学生",
    "hot_word_num": "422607"
  },
  {
    "hot_word": "上传收款二维码或卷入洗钱黑产",
    "hot_word_num": "402066"
  },
  {
    "hot_word": "明年我国将调整部分商品进口关税",
    "hot_word_num": "399891"
  },
  {
    "hot_word": "耿爽在联合国正面硬刚德国代表",
    "hot_word_num": "398390"
  },
  {
    "hot_word": "湖南卫视声明",
    "hot_word_num": "394145"
  },
  {
    "hot_word": "官方通报辛巴事件处理结果",
    "hot_word_num": "390489"
  },
  {
    "hot_word": "别再问为什么爱穿摇粒绒了",
    "hot_word_num": "390150"
  },
  {
    "hot_word": "小S晒许老二画作",
    "hot_word_num": "384494"
  },
  {
    "hot_word": "特朗普赦免15人",
    "hot_word_num": "379910"
  },
  {
    "hot_word": "港风豪门大小姐妆",
    "hot_word_num": "377824"
  },
  {
    "hot_word": "易烊千玺黑白线条套装",
    "hot_word_num": "358819"
  },
  {
    "hot_word": "北方人不加儿化音挑战",
    "hot_word_num": "345536"
  },
  {
    "hot_word": "THE9新歌DumbDumbBomb",
    "hot_word_num": "338046"
  },
  {
    "hot_word": "王霏霏跨年爬梯妆",
    "hot_word_num": "314805"
  },
  {
    "hot_word": "百岁之好一言为定",
    "hot_word_num": "298879"
  },
  {
    "hot_word": "男友的七宗罪",
    "hot_word_num": "297293"
  },
  {
    "hot_word": "警方通报游族CEO疑似中毒",
    "hot_word_num": "273314"
  },
  {
    "hot_word": "女神降临",
    "hot_word_num": "273031"
  },
  {
    "hot_word": "邓伦回应粉丝不喜欢郭敬明",
    "hot_word_num": "273027"
  },
  {
    "hot_word": "辛选回应燕窝事件处罚",
    "hot_word_num": "272998"
  },
  {
    "hot_word": "坐轮椅就别飙车了",
    "hot_word_num": "272995"
  },
  {
    "hot_word": "土星木星交会高清画面",
    "hot_word_num": "255630"
  },
  {
    "hot_word": "广东已有18万人接种新冠病毒疫苗",
    "hot_word_num": "250191"
  },
  {
    "hot_word": "钟南山说中国第一批疫苗要公布了",
    "hot_word_num": "248070"
  }
]
