[
  {
    "hot_word": "葛荟婕说汪峰把小苹果当成他的流量",
    "hot_word_num": "2519893"
  },
  {
    "hot_word": "天和核心舱发射入轨",
    "hot_word_num": "1839390"
  },
  {
    "hot_word": "时代少年团刷新记录",
    "hot_word_num": "1801618"
  },
  {
    "hot_word": "王俊凯弯腰低头听女生讲话",
    "hot_word_num": "1795973"
  },
  {
    "hot_word": "美团饿了么已逐步取消对骑士逐单处罚",
    "hot_word_num": "1402740"
  },
  {
    "hot_word": "王一博代言安踏",
    "hot_word_num": "1274122"
  },
  {
    "hot_word": "刷视频刷出的双胞胎姐妹系同卵双生",
    "hot_word_num": "1257207"
  },
  {
    "hot_word": "医生在91岁老人手背写下仨字",
    "hot_word_num": "1097582"
  },
  {
    "hot_word": "洛杉矶发生枪击一中国公民遇难",
    "hot_word_num": "938355"
  },
  {
    "hot_word": "一个人建了栋别墅",
    "hot_word_num": "796179"
  },
  {
    "hot_word": "刘亦菲再登VOGUE封面",
    "hot_word_num": "789989"
  },
  {
    "hot_word": "苹果iPad和Mac下半年预计将出现短缺",
    "hot_word_num": "789161"
  },
  {
    "hot_word": "尹正瘦了好多",
    "hot_word_num": "777221"
  },
  {
    "hot_word": "反食品浪费法通过",
    "hot_word_num": "773216"
  },
  {
    "hot_word": "张小斐为贾玲庆生",
    "hot_word_num": "766627"
  },
  {
    "hot_word": "情书重映定档",
    "hot_word_num": "761013"
  },
  {
    "hot_word": "不结婚老了真的会很惨吗",
    "hot_word_num": "750887"
  },
  {
    "hot_word": "中南财经政法大学",
    "hot_word_num": "744523"
  },
  {
    "hot_word": "全国婚检率提高至62.4%",
    "hot_word_num": "744216"
  },
  {
    "hot_word": "消除男尊女卑传宗接代等落后观念",
    "hot_word_num": "676107"
  },
  {
    "hot_word": "中国空间站核心舱发射",
    "hot_word_num": "663360"
  },
  {
    "hot_word": "哭着哭着拍了个自拍",
    "hot_word_num": "658385"
  },
  {
    "hot_word": "如何委婉的拒绝五一加班",
    "hot_word_num": "591838"
  },
  {
    "hot_word": "小李琳的前半生是杜冰雁后半生是主播",
    "hot_word_num": "586552"
  },
  {
    "hot_word": "丁程鑫缺席快本录制",
    "hot_word_num": "567170"
  },
  {
    "hot_word": "学医后才知道的知识",
    "hot_word_num": "502590"
  },
  {
    "hot_word": "印男子因新冠失去妻子和未出生孩子",
    "hot_word_num": "494003"
  },
  {
    "hot_word": "为什么你越来越沉默",
    "hot_word_num": "468970"
  },
  {
    "hot_word": "江南百景图",
    "hot_word_num": "456971"
  },
  {
    "hot_word": "五一东北特产成三亚爆款",
    "hot_word_num": "446964"
  },
  {
    "hot_word": "复兴号要开进西藏",
    "hot_word_num": "435916"
  },
  {
    "hot_word": "烟头60元一斤大爷大妈排队来卖",
    "hot_word_num": "404429"
  },
  {
    "hot_word": "被动式伏弟魔的经历",
    "hot_word_num": "389046"
  },
  {
    "hot_word": "四川雅安地震",
    "hot_word_num": "348626"
  },
  {
    "hot_word": "密室大逃脱",
    "hot_word_num": "345977"
  },
  {
    "hot_word": "刘耀文 你们没有自己的生活吗",
    "hot_word_num": "324610"
  },
  {
    "hot_word": "送外卖副处长谈感受",
    "hot_word_num": "317790"
  },
  {
    "hot_word": "原来我和吴亦凡没什么不同",
    "hot_word_num": "316981"
  },
  {
    "hot_word": "赵薇被冻结数百万股权",
    "hot_word_num": "307692"
  },
  {
    "hot_word": "杭州东站旅客已经人从众",
    "hot_word_num": "307297"
  },
  {
    "hot_word": "实拍印度医生休息室现场",
    "hot_word_num": "305576"
  },
  {
    "hot_word": "中国空间站在轨组装建造全面展开",
    "hot_word_num": "304368"
  },
  {
    "hot_word": "太阳时隔11年重返季后赛",
    "hot_word_num": "304287"
  },
  {
    "hot_word": "女子服药自杀未果起诉药店",
    "hot_word_num": "302495"
  },
  {
    "hot_word": "长歌行",
    "hot_word_num": "301397"
  },
  {
    "hot_word": "衡阳谎称捡小孩司机道歉",
    "hot_word_num": "300875"
  },
  {
    "hot_word": "恋与深空",
    "hot_word_num": "298782"
  },
  {
    "hot_word": "学区房",
    "hot_word_num": "298035"
  },
  {
    "hot_word": "R1SE新歌ZOOM",
    "hot_word_num": "297521"
  },
  {
    "hot_word": "刘宇把宠物狗叫做卡子哥",
    "hot_word_num": "297289"
  }
]
